django_nose_qunit/__init__.py
django_nose_qunit/conf.py
django_nose_qunit/models.py
django_nose_qunit/nose_plugin.py
django_nose_qunit/testcases.py
django_nose_qunit/urls.py
django_nose_qunit/views.py
django_nose_qunit/static/qunit-config.js
django_nose_qunit/static/qunit.css
django_nose_qunit/static/qunit.js
django_nose_qunit/templates/django_nose_qunit/list.html
django_nose_qunit/templates/django_nose_qunit/template.html
django_nose_qunit/tests/__init__.py
django_nose_qunit/tests/test_qunit_intro.py
django_nose_qunit-1.6.1.dist-info/DESCRIPTION.rst
django_nose_qunit-1.6.1.dist-info/entry_points.txt
django_nose_qunit-1.6.1.dist-info/METADATA
django_nose_qunit-1.6.1.dist-info/metadata.json
django_nose_qunit-1.6.1.dist-info/RECORD
django_nose_qunit-1.6.1.dist-info/top_level.txt
django_nose_qunit-1.6.1.dist-info/WHEEL
