Metadata-Version: 2.0
Name: django-nose-qunit
Version: 1.6.1
Summary: Integrate QUnit JavaScript tests into a Django test suite via nose
Home-page: https://github.com/safarijv/django-qunit-ci
Author: Jeremy Bowman
Author-email: jbowman@safaribooksonline.com
License: UNKNOWN
Platform: UNKNOWN
Classifier: Development Status :: 5 - Production/Stable
Classifier: Environment :: Web Environment
Classifier: Framework :: Django
Classifier: Framework :: Django :: 1.6
Classifier: Framework :: Django :: 1.7
Classifier: Framework :: Django :: 1.8
Classifier: Framework :: Django :: 1.9
Classifier: Intended Audience :: Developers
Classifier: License :: OSI Approved :: BSD License
Classifier: Natural Language :: English
Classifier: Operating System :: OS Independent
Classifier: Programming Language :: Python
Classifier: Programming Language :: Python :: 2
Classifier: Programming Language :: Python :: 2.7
Classifier: Programming Language :: Python :: 3
Classifier: Programming Language :: Python :: 3.4
Classifier: Programming Language :: Python :: 3.5
Classifier: Topic :: Software Development :: Testing
Requires-Dist: django-nose
Requires-Dist: sbo-selenium (>=0.4.0)
